cpu.sv
module IMemory(
    input  wire [31:0]   pc,
    output logic [31:0]  instr
);

always_comb begin
    case (pc)
        32'h0000 : instr = 32'h0000a303; // lw x6, 0(x1)
        32'h0004 : instr = 32'h00612023; // sw x6, 0(x2)
        default: begin
            instr = 32'h0000;
            $display("die");
        end
    endcase
end

endmodule

module Regfile(
    input   wire          clk,
    input   wire          rst,

    // 読み込み
    input  wire   [4:0]   addr1,
    output logic [31:0]   rd1,
    input  wire   [4:0]   addr2,
    output logic [31:0]   rd2,

    // 書き込み
    input  wire  [4:0]    addr3,
    input  wire           we3,
    input  wire [31:0]    wd3
);

logic [31:0] regfile [0:31];

always_ff @(posedge clk) begin
    if (rst) begin
        for (int i = 0; i < 32; i++) begin
            regfile[i] <= 32'h0;
        end
    end else begin
        if (we3) begin
            regfile[addr3] <= wd3;
        end
    end
end

always_comb begin
    // rd1にaddr1の中身を出力
    rd1 = regfile[addr1];

    // rd2にaddr2の中身を出力
    rd2 = regfile[addr2];
end

endmodule

module DMemory (
    input  wire             clk,
    input  wire [31: 0]     address,
    input  wire [31: 0]     write_data,
    input  wire             write_enable, 
    output logic [31: 0]     read_data
);

logic [31:0] dmemory [0:1023];

always_ff @(posedge clk) begin
    if(write_enable) begin
        dmemory[address] <= write_data;
    end
end

always_comb begin
    read_data = dmemory[address];
end

endmodule

module ALU (
    input  wire  [2:0]   alu_control,
    input  wire [31:0]   srca,
    input  wire [31:0]   srcb,

    output logic [31:0]   alu_result
);

always_comb begin
    case (alu_control)
        3'b000 : alu_result = srca + srcb;
        3'b001 : alu_result = srca - srcb;
        3'b010 : alu_result = srca & srcb;
        3'b011 : alu_result = srca | srcb;
        3'b101 : alu_result = srca < srcb;
        default: begin
            alu_result = 32'hDEADBEEF;
            $display("Unknown ALU command.");
        end
    endcase
end

// assign alu_result = 32'hDEADBEEF;

endmodule

module CPU(
    input   wire    clk,
    input   wire    rst
);
    logic   [31: 0] pc;
    logic   [31: 0] instr;
    logic   [2:0]   alu_control;

    IMemory instruction_memory(
        .pc(pc),
        .instr(instr)
    );
    
    always_comb begin
        alu_control = 3'b000;
    end

    wire [31: 0] pc_next = pc + 4;
    always_ff @(posedge clk) begin
        if (rst) begin
            pc <= 0;
        end
        else begin
            pc <= pc_next;
        end
    end

    logic   [31: 0] rd1, rd2;

    // for I-format
    Regfile reg_file(
        .clk(clk),
        .rst(rst),
        
        .addr1(instr[19: 15]),
        .rd1(rd1),
        
        .addr3(instr[11: 7]),
        .wd3(memory_read_data)
    );

    //logic   data_address = rd1 + instr[11: 0];
    /*
    function 関数名(
        input 入力1,
        input 入力2
    );
        関数名 = 入力1 + 入力2;
    endfunction
    */
    function [31: 0] extend(input [11:0] imm);
        extend = 32'(signed'(imm[11:0]));
    endfunction

    logic   [31:0] alu_result;
    ALU alu(
        .alu_control(alu_control),
        .srca(rd1),
        .srcb(extend(instr[31:20])),
        .alu_result(alu_result)
    );

    logic   [31: 0] memory_read_data;

    DMemory data_memory(
        .clk(clk),
        .address(alu_result),
        .read_data(memory_read_data),
        .write_enable(1'b0)
    );
endmodule

cpu_test.sv
`default_nettype none
`timescale 1ns/1ps

module cpu_test();
    logic clk;
    logic rst;
    
    CPU cpu(.clk(clk), .rst(rst));

    initial begin
        $dumpfile("cpu.vcd");
        $dumpvars(0, cpu, cpu.reg_file.regfile);
        clk = 0;

        rst = 1;
        @(posedge clk)
        @(posedge clk)
        rst = 0;
        #1000
        $finish;
    end
    always #(5) begin
        clk <= ~clk;
    end

endmodule
`default_nettype wire

cpu.vcd
$date
	Sat Sep  9 23:08:17 2023
$end
$version
	Icarus Verilog
$end
$timescale
	1ps
$end
$scope module cpu_test $end
$scope module cpu $end
$var wire 1 ! clk $end
$var wire 1 " rst $end
$var wire 32 # rd1 [31:0] $end
$var wire 32 $ pc_next [31:0] $end
$var wire 32 % memory_read_data [31:0] $end
$var wire 32 & instr [31:0] $end
$var wire 32 ' alu_result [31:0] $end
$var reg 3 ( alu_control [2:0] $end
$var reg 32 ) pc [31:0] $end
$scope function extend $end
$var reg 12 * imm [11:0] $end
$upscope $end
$scope module alu $end
$var wire 3 + alu_control [2:0] $end
$var wire 32 , srcb [31:0] $end
$var wire 32 - srca [31:0] $end
$var reg 32 . alu_result [31:0] $end
$upscope $end
$scope module data_memory $end
$var wire 32 / address [31:0] $end
$var wire 1 ! clk $end
$var wire 32 0 write_data [31:0] $end
$var wire 1 1 write_enable $end
$var reg 32 2 read_data [31:0] $end
$upscope $end
$scope module instruction_memory $end
$var wire 32 3 pc [31:0] $end
$var reg 32 4 instr [31:0] $end
$upscope $end
$scope module reg_file $end
$var wire 5 5 addr1 [4:0] $end
$var wire 5 6 addr2 [4:0] $end
$var wire 5 7 addr3 [4:0] $end
$var wire 1 ! clk $end
$var wire 1 " rst $end
$var wire 32 8 wd3 [31:0] $end
$var wire 1 9 we3 $end
$var reg 32 : rd1 [31:0] $end
$var reg 32 ; rd2 [31:0] $end
$scope begin $ivl_for_loop0 $end
$var integer 32 < i [31:0] $end
$upscope $end
$upscope $end
$upscope $end
$upscope $end
$enddefinitions $end
$comment Show the parameter values. $end
$dumpall
$end
#0
$dumpvars
b0 <
bx ;
bx :
z9
bx 8
b0 7
bz 6
b0 5
b0 4
bx 3
bx 2
01
bz 0
bx /
bx .
bx -
b0 ,
b0 +
b0 *
bx )
b0 (
bx '
b0 &
bx %
bx $
bx #
1"
0!
$end
#5000
b0 '
b0 .
b0 /
b110 7
b1 5
b0 #
b0 -
b0 :
b1010001100000011 &
b1010001100000011 4
b100 $
b0 )
b0 3
b100000 <
1!
#10000
0!
#15000
b100000 <
0"
1!
#20000
0!
#25000
b110 '
b110 .
b110 /
b110 ,
b110 *
b0 7
b10 5
b11000010010000000100011 &
b11000010010000000100011 4
b1000 $
b100 )
b100 3
1!
#30000
0!
#35000
b0 '
b0 .
b0 /
b0 ,
b0 *
b0 5
b0 &
b0 4
b1100 $
b1000 )
b1000 3
1!
#40000
0!
#45000
b10000 $
b1100 )
b1100 3
1!
#50000
0!
#55000
b10100 $
b10000 )
b10000 3
1!
#60000
0!
#65000
b11000 $
b10100 )
b10100 3
1!
#70000
0!
#75000
b11100 $
b11000 )
b11000 3
1!
#80000
0!
#85000
b100000 $
b11100 )
b11100 3
1!
#90000
0!
#95000
b100100 $
b100000 )
b100000 3
1!
#100000
0!
#105000
b101000 $
b100100 )
b100100 3
1!
#110000
0!
#115000
b101100 $
b101000 )
b101000 3
1!
#120000
0!
#125000
b110000 $
b101100 )
b101100 3
1!
#130000
0!
#135000
b110100 $
b110000 )
b110000 3
1!
#140000
0!
#145000
b111000 $
b110100 )
b110100 3
1!
#150000
0!
#155000
b111100 $
b111000 )
b111000 3
1!
#160000
0!
#165000
b1000000 $
b111100 )
b111100 3
1!
#170000
0!
#175000
b1000100 $
b1000000 )
b1000000 3
1!
#180000
0!
#185000
b1001000 $
b1000100 )
b1000100 3
1!
#190000
0!
#195000
b1001100 $
b1001000 )
b1001000 3
1!
#200000
0!
#205000
b1010000 $
b1001100 )
b1001100 3
1!
#210000
0!
#215000
b1010100 $
b1010000 )
b1010000 3
1!
#220000
0!
#225000
b1011000 $
b1010100 )
b1010100 3
1!
#230000
0!
#235000
b1011100 $
b1011000 )
b1011000 3
1!
#240000
0!
#245000
b1100000 $
b1011100 )
b1011100 3
1!
#250000
0!
#255000
b1100100 $
b1100000 )
b1100000 3
1!
#260000
0!
#265000
b1101000 $
b1100100 )
b1100100 3
1!
#270000
0!
#275000
b1101100 $
b1101000 )
b1101000 3
1!
#280000
0!
#285000
b1110000 $
b1101100 )
b1101100 3
1!
#290000
0!
#295000
b1110100 $
b1110000 )
b1110000 3
1!
#300000
0!
#305000
b1111000 $
b1110100 )
b1110100 3
1!
#310000
0!
#315000
b1111100 $
b1111000 )
b1111000 3
1!
#320000
0!
#325000
b10000000 $
b1111100 )
b1111100 3
1!
#330000
0!
#335000
b10000100 $
b10000000 )
b10000000 3
1!
#340000
0!
#345000
b10001000 $
b10000100 )
b10000100 3
1!
#350000
0!
#355000
b10001100 $
b10001000 )
b10001000 3
1!
#360000
0!
#365000
b10010000 $
b10001100 )
b10001100 3
1!
#370000
0!
#375000
b10010100 $
b10010000 )
b10010000 3
1!
#380000
0!
#385000
b10011000 $
b10010100 )
b10010100 3
1!
#390000
0!
#395000
b10011100 $
b10011000 )
b10011000 3
1!
#400000
0!
#405000
b10100000 $
b10011100 )
b10011100 3
1!
#410000
0!
#415000
b10100100 $
b10100000 )
b10100000 3
1!
#420000
0!
#425000
b10101000 $
b10100100 )
b10100100 3
1!
#430000
0!
#435000
b10101100 $
b10101000 )
b10101000 3
1!
#440000
0!
#445000
b10110000 $
b10101100 )
b10101100 3
1!
#450000
0!
#455000
b10110100 $
b10110000 )
b10110000 3
1!
#460000
0!
#465000
b10111000 $
b10110100 )
b10110100 3
1!
#470000
0!
#475000
b10111100 $
b10111000 )
b10111000 3
1!
#480000
0!
#485000
b11000000 $
b10111100 )
b10111100 3
1!
#490000
0!
#495000
b11000100 $
b11000000 )
b11000000 3
1!
#500000
0!
#505000
b11001000 $
b11000100 )
b11000100 3
1!
#510000
0!
#515000
b11001100 $
b11001000 )
b11001000 3
1!
#520000
0!
#525000
b11010000 $
b11001100 )
b11001100 3
1!
#530000
0!
#535000
b11010100 $
b11010000 )
b11010000 3
1!
#540000
0!
#545000
b11011000 $
b11010100 )
b11010100 3
1!
#550000
0!
#555000
b11011100 $
b11011000 )
b11011000 3
1!
#560000
0!
#565000
b11100000 $
b11011100 )
b11011100 3
1!
#570000
0!
#575000
b11100100 $
b11100000 )
b11100000 3
1!
#580000
0!
#585000
b11101000 $
b11100100 )
b11100100 3
1!
#590000
0!
#595000
b11101100 $
b11101000 )
b11101000 3
1!
#600000
0!
#605000
b11110000 $
b11101100 )
b11101100 3
1!
#610000
0!
#615000
b11110100 $
b11110000 )
b11110000 3
1!
#620000
0!
#625000
b11111000 $
b11110100 )
b11110100 3
1!
#630000
0!
#635000
b11111100 $
b11111000 )
b11111000 3
1!
#640000
0!
#645000
b100000000 $
b11111100 )
b11111100 3
1!
#650000
0!
#655000
b100000100 $
b100000000 )
b100000000 3
1!
#660000
0!
#665000
b100001000 $
b100000100 )
b100000100 3
1!
#670000
0!
#675000
b100001100 $
b100001000 )
b100001000 3
1!
#680000
0!
#685000
b100010000 $
b100001100 )
b100001100 3
1!
#690000
0!
#695000
b100010100 $
b100010000 )
b100010000 3
1!
#700000
0!
#705000
b100011000 $
b100010100 )
b100010100 3
1!
#710000
0!
#715000
b100011100 $
b100011000 )
b100011000 3
1!
#720000
0!
#725000
b100100000 $
b100011100 )
b100011100 3
1!
#730000
0!
#735000
b100100100 $
b100100000 )
b100100000 3
1!
#740000
0!
#745000
b100101000 $
b100100100 )
b100100100 3
1!
#750000
0!
#755000
b100101100 $
b100101000 )
b100101000 3
1!
#760000
0!
#765000
b100110000 $
b100101100 )
b100101100 3
1!
#770000
0!
#775000
b100110100 $
b100110000 )
b100110000 3
1!
#780000
0!
#785000
b100111000 $
b100110100 )
b100110100 3
1!
#790000
0!
#795000
b100111100 $
b100111000 )
b100111000 3
1!
#800000
0!
#805000
b101000000 $
b100111100 )
b100111100 3
1!
#810000
0!
#815000
b101000100 $
b101000000 )
b101000000 3
1!
#820000
0!
#825000
b101001000 $
b101000100 )
b101000100 3
1!
#830000
0!
#835000
b101001100 $
b101001000 )
b101001000 3
1!
#840000
0!
#845000
b101010000 $
b101001100 )
b101001100 3
1!
#850000
0!
#855000
b101010100 $
b101010000 )
b101010000 3
1!
#860000
0!
#865000
b101011000 $
b101010100 )
b101010100 3
1!
#870000
0!
#875000
b101011100 $
b101011000 )
b101011000 3
1!
#880000
0!
#885000
b101100000 $
b101011100 )
b101011100 3
1!
#890000
0!
#895000
b101100100 $
b101100000 )
b101100000 3
1!
#900000
0!
#905000
b101101000 $
b101100100 )
b101100100 3
1!
#910000
0!
#915000
b101101100 $
b101101000 )
b101101000 3
1!
#920000
0!
#925000
b101110000 $
b101101100 )
b101101100 3
1!
#930000
0!
#935000
b101110100 $
b101110000 )
b101110000 3
1!
#940000
0!
#945000
b101111000 $
b101110100 )
b101110100 3
1!
#950000
0!
#955000
b101111100 $
b101111000 )
b101111000 3
1!
#960000
0!
#965000
b110000000 $
b101111100 )
b101111100 3
1!
#970000
0!
#975000
b110000100 $
b110000000 )
b110000000 3
1!
#980000
0!
#985000
b110001000 $
b110000100 )
b110000100 3
1!
#990000
0!
#995000
b110001100 $
b110001000 )
b110001000 3
1!
#1000000
0!
#1005000
b110010000 $
b110001100 )
b110001100 3
1!
#1010000
0!
#1015000
b110010100 $
b110010000 )
b110010000 3
1!
